pantheon/__init__.py
pantheon/gods.py
pantheon/names.py
pantheon/pantheons.py
pantheon/process.py
pantheon/tokens.py
pantheon/data/skipwords.txt
pantheon/data/corpora/american-pomology.json
pantheon/data/corpora/ant-eatig-frog.json
pantheon/data/corpora/astounding-stories-april-1930.json
pantheon/data/corpora/astounding-stories-feb-1930.json
pantheon/data/corpora/astounding-stories-march-1930.json
pantheon/data/corpora/bloodletting-instruments.json
pantheon/data/corpora/book-of-the-damned.json
pantheon/data/corpora/british-birds-in-their-haunts.json
pantheon/data/corpora/culinary-poisons.json
pantheon/data/corpora/deductive-logic.json
pantheon/data/corpora/dutch-fairy-tales.json
pantheon/data/corpora/english-fairy-tales.json
pantheon/data/corpora/flowers-of-the-farm.json
pantheon/data/corpora/four-weird-tales.json
pantheon/data/corpora/game-birds-and-fishes.json
pantheon/data/corpora/ghost-stories-of-an-antiquary.json
pantheon/data/corpora/hardy-flowering-shrubs.json
pantheon/data/corpora/historic-ornament.json
pantheon/data/corpora/insectivorous-plants.json
pantheon/data/corpora/irish-fairy-tales.json
pantheon/data/corpora/memorabilia-mathematica.json
pantheon/data/corpora/persian-fairy-tales.json
pantheon/data/corpora/principles-of-gothic-architecture.json
pantheon/data/corpora/roumanian-fairy-tales.json
pantheon/data/corpora/rural-architecture.json
pantheon/data/corpora/russian-fairy-tales.json
pantheon/data/corpora/surgical-anatomy.json
pantheon/data/corpora/the-badger.json
pantheon/data/corpora/the-crock-of-gold.json
pantheon/data/corpora/the-kama-sutra.json
pantheon/data/corpora/the-king-in-yellow.json
pantheon/data/corpora/the-night-land.json
pantheon/data/corpora/the-ruby-of-kishmoor.json
pantheon/data/corpora/the-satyricon.json
pantheon/data/corpora/the-shunned-house.json
pantheon/data/corpora/venus-in-furs.json
pantheon/data/corpora/viking-tales.json
pantheon/data/corpora/welsh-fairy-tales.json
pantheon_generator-2.0.0.dist-info/METADATA
pantheon_generator-2.0.0.dist-info/RECORD
pantheon_generator-2.0.0.dist-info/WHEEL
pantheon_generator-2.0.0.dist-info/top_level.txt
