Metadata-Version: 2.1
Name: pantheon-generator
Version: 2.0.0
Summary: A module for generating lists of related dieties
Home-page: https://github.com/carawarner/pantheon
Author: Cara Warner
Author-email: procgenitor@gmail.com
License: Apache License 2.0
Project-URL: Bug Reports, https://github.com/carawarner/pantheon/issues
Project-URL: Source, https://github.com/carawarner/pantheon
Keywords: procgen nlg creativity
Platform: UNKNOWN
Requires-Dist: nltk
Requires-Dist: numpy
Requires-Dist: spacy
